fina/__init__.py
fina/example.py
fina-0.0.1.dist-info/LICENSE
fina-0.0.1.dist-info/METADATA
fina-0.0.1.dist-info/WHEEL
fina-0.0.1.dist-info/top_level.txt
fina-0.0.1.dist-info/RECORD
