Metadata-Version: 2.1
Name: fina
Version: 0.0.1
Summary: Python package to build financial data
Author-email: Jaehyun Shin <keepcosmos@gmail.com>
Project-URL: Homepage, https://github.com/keepcosmos/fina
Project-URL: Bug Tracker, https://github.com/keepcosmos/fina/issues
Classifier: Programming Language :: Python :: 3
Classifier: License :: OSI Approved :: MIT License
Classifier: Operating System :: OS Independent
Requires-Python: >=3.7
License-File: LICENSE
